odoo/addons/shopinvader_restapi_sale_packaging/README.rst
odoo/addons/shopinvader_restapi_sale_packaging/__init__.py
odoo/addons/shopinvader_restapi_sale_packaging/__manifest__.py
odoo/addons/shopinvader_restapi_sale_packaging/i18n/shopinvader_restapi_sale_packaging.pot
odoo/addons/shopinvader_restapi_sale_packaging/readme/CONTRIBUTORS.rst
odoo/addons/shopinvader_restapi_sale_packaging/readme/CREDITS.rst
odoo/addons/shopinvader_restapi_sale_packaging/readme/DESCRIPTION.rst
odoo/addons/shopinvader_restapi_sale_packaging/services/__init__.py
odoo/addons/shopinvader_restapi_sale_packaging/services/abstract_sale.py
odoo/addons/shopinvader_restapi_sale_packaging/services/cart.py
odoo/addons/shopinvader_restapi_sale_packaging/services/packaging_mixin.py
odoo/addons/shopinvader_restapi_sale_packaging/static/description/index.html
odoo/addons/shopinvader_restapi_sale_packaging/tests/__init__.py
odoo/addons/shopinvader_restapi_sale_packaging/tests/common.py
odoo/addons/shopinvader_restapi_sale_packaging/tests/test_cart.py
odoo/addons/shopinvader_restapi_sale_packaging/tests/test_sale.py
odoo_addon_shopinvader_restapi_sale_packaging-16.0.1.1.0.dist-info/METADATA
odoo_addon_shopinvader_restapi_sale_packaging-16.0.1.1.0.dist-info/WHEEL
odoo_addon_shopinvader_restapi_sale_packaging-16.0.1.1.0.dist-info/top_level.txt
odoo_addon_shopinvader_restapi_sale_packaging-16.0.1.1.0.dist-info/RECORD
