Metadata-Version: 2.1
Name: odoo-addon-shopinvader-restapi-sale-packaging
Version: 16.0.1.1.0
Summary: Shopinvader Restapi Sale Packaging
Home-page: https://github.com/shopinvader/odoo-shopinvader
Author: Camptocamp, ACSONE
License: AGPL-3
Platform: UNKNOWN
Classifier: Programming Language :: Python
Classifier: Framework :: Odoo
Classifier: Framework :: Odoo :: 16.0
Classifier: License :: OSI Approved :: GNU Affero General Public License v3
Requires-Python: >=3.10
Requires-Dist: odoo-addon-shopinvader-product <16.1dev,>=16.0dev
Requires-Dist: odoo-addon-shopinvader-product-sale-packaging <16.1dev,>=16.0dev
Requires-Dist: odoo-addon-shopinvader-restapi <16.1dev,>=16.0dev
Requires-Dist: odoo <16.1dev,>=16.0a
